{
  "emails": [
    {
      "sender": "Patricia DELEAU",
      "subject": "✨La Peña - Newsletter Février 2026 ✨ Planning des événements, Agenda des événements 2026, Présentation des nouveaux Peñistas.",
      "time": "12:34",
      "unread": true
    },
    {
      "sender": "ArtStation",
      "subject": "Shop Winter Sale Deals on the ArtStation Marketplace!",
      "time": "10:57",
      "unread": true
    },
    {
      "sender": "Maleducat",
      "subject": "Valoración de reserva en Maleducat",
      "time": "09:21",
      "unread": true
    },
    {
      "sender": "sergio saravia (via Google Sheets)",
      "subject": "Spreadsheet shared with you: ‘Cierre Proyecto Exquisite’",
      "time": "14:56",
      "unread": true
    },
    {
      "sender": "sgseaux@gmail.com",
      "subject": "Exquisite Daily Report - 2026-01-28",
      "time": "10:28",
      "unread": true
    },
    {
      "sender": "Juliette Lavedan-Forment",
      "subject": "Invitation: Rdv Susana colegio @ Fri 6 Feb 2026 1:30pm - 2:30pm (CET) (hartostudio@gmail.com)",
      "time": "08:18",
      "unread": true
    },
    {
      "sender": "UPS",
      "subject": "Hoy tienes una recogida",
      "time": "06:40",
      "unread": true
    },
    {
      "sender": "Núria  Nadal",
      "subject": "2026 Presupuesto Asesoría HARTO ATELIER",
      "time": "12:53",
      "unread": true
    },
    {
      "sender": "Vercel",
      "subject": "New sign-in detected on your Vercel account",
      "time": "15:43",
      "unread": true
    },
    {
      "sender": "sgseaux@gmail.com",
      "subject": "Exquisite Daily Report - 2026-01-26",
      "time": "15:19",
      "unread": true
    }
  ],
  "unreadCount": 10,
  "updated": "2026-01-30T13:30:56Z"
}
