[
  {
    "username": "JohnCena",
    "name": "John Cena",
    "bio": "A forum of thoughts and perspectives designed to ignite conversations and actions leading to growth, and occasional self promotion. #NeverGiveUp #RiseAboveHate",
    "followers": 12701779,
    "following": 1073817,
    "verified": true,
    "category": "ordinals",
    "url": "https://x.com/JohnCena",
    "location": "West Newbury, MA",
    "created": "Sat May 08 17:43:50 +0000 2010",
    "tweets": 8192
  },
  {
    "username": "danheld",
    "name": "Dan Held",
    "bio": "Investing in Bitcoin DeFi and Space. Marketing Advisor @TaprootWizards, Prev: Head of Marketing @Krakenfx | Growth @Uber @Blockchain.",
    "followers": 836214,
    "following": 1079,
    "verified": true,
    "category": "ordinals",
    "url": "https://x.com/danheld",
    "location": "The moon",
    "created": "Tue Jul 16 15:50:59 +0000 2013",
    "tweets": 79892
  },
  {
    "username": "ZachBoychuk",
    "name": "Zach Boychuk\ud83d\udc0d",
    "bio": "\ud83c\udfd2Pro Hockey Player & Part time Meme/NFT Trader \ud83d\ude80 \ud83c\udf0c| (not financial advice) \ud83d\udcc8\ud83d\ude80#Bitcoin, Ethereum, Solana",
    "followers": 768236,
    "following": 656429,
    "verified": true,
    "category": "ordinals",
    "url": "https://x.com/ZachBoychuk",
    "location": null,
    "created": "Tue Nov 17 05:36:14 +0000 2009",
    "tweets": 11245
  },
  {
    "username": "Jeremybtc",
    "name": "Jeremy",
    "bio": "Co-Founder @GlydeGG | unemployed (btc) since 17\u2019 | chief of vibes and imaginary money | advisor @OKX & @wallet | free trading group: https://t.co/UdrhtRk8uh | Dubai \ud83c\udde6\ud83c\uddea",
    "followers": 270564,
    "following": 27311,
    "verified": true,
    "category": "ordinals",
    "url": "https://x.com/Jeremybtc",
    "location": "Business \u2192",
    "created": "Thu Nov 04 07:35:08 +0000 2021",
    "tweets": 741128
  },
  {
    "username": "djsamhouse",
    "name": "djsamhouse",
    "bio": "Front-run the zeitgeist. \ud83d\udd2e #bitcoin",
    "followers": 243470,
    "following": 2869,
    "verified": true,
    "category": "ordinals",
    "url": "https://x.com/djsamhouse",
    "location": "Los Angeles",
    "created": "Wed Oct 01 04:47:52 +0000 2008",
    "tweets": 18151
  },
  {
    "username": "0xSweep",
    "name": "Sweep",
    "bio": "Co-Founder @GlydeGG | #Bitcoin | angel investor | crypto since 17' | advisor @okx @wallet | free trading group: https://t.co/w2U7XhOH1P | Dubai \ud83c\udde6\ud83c\uddea",
    "followers": 242202,
    "following": 16307,
    "verified": true,
    "category": "ordinals",
    "url": "https://x.com/0xSweep",
    "location": "Business \u2794",
    "created": "Fri Mar 26 10:38:55 +0000 2021",
    "tweets": 931480
  },
  {
    "username": "LeonidasNFT",
    "name": "Leonidas \ud83e\udde1 $DOG",
    "bio": "Building @ZapApp | Host @TheOrdinalShow",
    "followers": 241392,
    "following": 7258,
    "verified": true,
    "category": "ordinals",
    "url": "https://x.com/LeonidasNFT",
    "location": "",
    "created": "Fri Apr 15 04:31:31 +0000 2016",
    "tweets": 79092
  },
  {
    "username": "BLIFEProtocol",
    "name": "BLIFE Protocol",
    "bio": "Bringing Web3 to Bitcoin with the backing of Animoca Brands.\nMerged with @Portalcoin",
    "followers": 231370,
    "following": 163,
    "verified": true,
    "category": "ordinals",
    "url": "https://x.com/BLIFEProtocol",
    "location": "Metaverse",
    "created": "Wed Jan 24 11:22:14 +0000 2024",
    "tweets": 1892
  },
  {
    "username": "GoMining_token",
    "name": "GoMining",
    "bio": "Earn Bitcoin. Use Bitcoin. One App  \n\nMine, grow, and pay with BTC \u2014 all in one app \u2022 Powered by $GOMINING",
    "followers": 220153,
    "following": 762,
    "verified": false,
    "category": "ordinals",
    "url": "https://x.com/GoMining_token",
    "location": "",
    "created": "Sat May 15 16:58:31 +0000 2021",
    "tweets": 6283
  },
  {
    "username": "BoredWeb3",
    "name": "hold.btc",
    "bio": "maker of https://t.co/uRYekJaLJ4 & https://t.co/ffGDDmZlS5\n\nappend .onl to your domain and seamless access to bitcoin permaweb",
    "followers": 188268,
    "following": 728,
    "verified": true,
    "category": "ordinals",
    "url": "https://x.com/BoredWeb3",
    "location": "Ordinals Name Link",
    "created": "Sat Aug 16 03:15:53 +0000 2014",
    "tweets": 24178
  },
  {
    "username": "dondracoxxx",
    "name": "Don Draco",
    "bio": "Making things Raw \ud83e\udd69\ud83e\udde8 Built the biggest social network. Using BTC to fuck up some punk ass elites. If you only have BTC & no bullets are you really a MAXI \ud83d\udca5",
    "followers": 179552,
    "following": 975,
    "verified": true,
    "category": "ordinals",
    "url": "https://x.com/dondracoxxx",
    "location": "Miami, FL",
    "created": "Wed Sep 20 01:48:52 +0000 2023",
    "tweets": 2275
  },
  {
    "username": "Defi_Rocketeer",
    "name": "Defi Rocketeer",
    "bio": "OG Investor $BTC $ETH | Web3 Writer | KOL Manager | Partner of @ton_blockchain | PM: https://t.co/WUoExkO67g\n\nWork at: https://t.co/oIC5o67qU9",
    "followers": 167401,
    "following": 4753,
    "verified": true,
    "category": "ordinals",
    "url": "https://x.com/Defi_Rocketeer",
    "location": "",
    "created": "Thu Feb 03 08:05:36 +0000 2011",
    "tweets": 50137
  },
  {
    "username": "CryptoMaelle",
    "name": "Crypto Maelle",
    "bio": "Bitcoin & #crypto | Hodler | WEB3 Community Building | #BTC & #Altcoins Educator | TRADER | #GameFi \ud83d\udc8e | #DeFi + #NFT + #WEB3 | Not Financial adviser. DYOR",
    "followers": 163855,
    "following": 3947,
    "verified": true,
    "category": "ordinals",
    "url": "https://x.com/CryptoMaelle",
    "location": "Frenchtown, MI",
    "created": "Mon Jul 09 14:12:42 +0000 2018",
    "tweets": 68805
  },
  {
    "username": "TO",
    "name": "TO",
    "bio": "making cartoons & games @pizzaninjas investing @btcfrontierfund",
    "followers": 147017,
    "following": 13621,
    "verified": true,
    "category": "ordinals",
    "url": "https://x.com/TO",
    "location": null,
    "created": "Thu Jun 07 05:10:03 +0000 2007",
    "tweets": 64032
  },
  {
    "username": "MEonBTC",
    "name": "Magic Eden on Bitcoin \ud83d\udfe7",
    "bio": "The #1 Bitcoin DEX and Liquidity Layer for Ordinals and Runes brought to you by @MagicEden | Support: https://t.co/0OPSg9YpoB Not for US or UK audiences \ud83d\udfe7",
    "followers": 99134,
    "following": 758,
    "verified": true,
    "category": "ordinals",
    "url": "https://x.com/MEonBTC",
    "location": "On Chain",
    "created": "Fri Mar 17 13:13:01 +0000 2023",
    "tweets": 9279
  },
  {
    "username": "domodata",
    "name": "domo",
    "bio": "Having fun with bitcoin @L1Fxyz",
    "followers": 88361,
    "following": 1881,
    "verified": true,
    "category": "ordinals",
    "url": "https://x.com/domodata",
    "location": "",
    "created": "Wed Sep 02 15:04:43 +0000 2020",
    "tweets": 856
  },
  {
    "username": "btcordinal",
    "name": "BTC MACHINE\ud83e\udd16 - BTC VIRUS\ud83e\udda0",
    "bio": "BTC MACHINE \ud83d\udd36 Play @satoriammorpg\n$ZBIT \ud83d\udc99 Join https://t.co/YNmMGKvhK8",
    "followers": 83795,
    "following": 1019,
    "verified": true,
    "category": "ordinals",
    "url": "https://x.com/btcordinal",
    "location": "Bitcoin",
    "created": "Mon Nov 21 18:33:07 +0000 2022",
    "tweets": 28025
  },
  {
    "username": "OnChainMonkey",
    "name": "OnChainMonkey\u00ae",
    "bio": "We Innovate to Make Bitcoin Great.\n\nhttps://t.co/hAczAdCxKQ",
    "followers": 82404,
    "following": 3324,
    "verified": true,
    "category": "ordinals",
    "url": "https://x.com/OnChainMonkey",
    "location": "",
    "created": "Sun Sep 12 12:54:14 +0000 2021",
    "tweets": 22188
  },
  {
    "username": "GenzioCo",
    "name": "Genzio Media & Marketing",
    "bio": "Media & Marketing Ecosystem. We help brands grow sustainably. Partners:@EthereumDenver, @kbwofficial, @consensus2025, @TheBitcoinConf.",
    "followers": 77520,
    "following": 6340,
    "verified": false,
    "category": "ordinals",
    "url": "https://x.com/GenzioCo",
    "location": "Las Vegas, NV",
    "created": "Fri Jan 14 17:31:08 +0000 2022",
    "tweets": 16479
  },
  {
    "username": "ZK_shark",
    "name": "zk-\ud83e\udd88",
    "bio": "_\u0334\u0321\u0327\u0327\u0322\u0327\u032d\u033a\u0323\u0356\u032c\u0332\u0339\u032c\u032d\u0330\u0318\u032b\u034e\u0339\u0353\u0339\u032e\u0354\u0329\u0326\u032b\u032e\u0330\u0355\u031d\u031d\u0332\u033a\u035a\u032a\u031d\u0330\u0332\u0329\u0339\u0331\u0324\u0352\u0304\u0300\u0305\u030d\u0350\u0313\u0300\u034a\u030c\u030d\u030e\u0310\u0314\u034b\u0306\u0308\u0301\u033d\u0300\u0313\u0300\u0300\u033e\u0301\u033e\u0311\u0357\u0301\u0309\u0303\u030e\u033e\u030a\u0351\u0306\u0313\u0300\u0312\u030e\u0308\u0301\u034b\u035c\u0345   @Parasite_wtf                                        @OrdinalMaxiBiz",
    "followers": 75562,
    "following": 7385,
    "verified": true,
    "category": "ordinals",
    "url": "https://x.com/ZK_shark",
    "location": "",
    "created": "Sat Jan 29 21:42:59 +0000 2022",
    "tweets": 12315
  },
  {
    "username": "justintrimble",
    "name": "Justin Trimble",
    "bio": "Co-founder: @BrainDrops_art. Investor: BTC/ETH/Tech. Collector: CryptoPunks, Chromie Squiggles, XCOPY, beeple, MoonCats, Gen Art (AI & Algo), Osinachi...",
    "followers": 71439,
    "following": 2467,
    "verified": true,
    "category": "ordinals",
    "url": "https://x.com/justintrimble",
    "location": "Terminally online",
    "created": "Wed Sep 10 15:03:43 +0000 2008",
    "tweets": 49593
  },
  {
    "username": "OrdzGames",
    "name": "Ordz Games",
    "bio": "1st Gaming Project on #Bitcoin\nPowered by $ORDG, 1st BRC-20 token with utility\n& Rune #111 GAME\u2022OF\u2022BITCOIN",
    "followers": 68331,
    "following": 2613,
    "verified": true,
    "category": "ordinals",
    "url": "https://x.com/OrdzGames",
    "location": "183333.bitmap",
    "created": "Thu Apr 04 08:39:00 +0000 2013",
    "tweets": 5804
  },
  {
    "username": "decodejar",
    "name": "Decode",
    "bio": "#Bitcoin & Crypto Market Intelligence | https://t.co/pTW6aRa3ul",
    "followers": 65914,
    "following": 498,
    "verified": true,
    "category": "ordinals",
    "url": "https://x.com/decodejar",
    "location": "Not financial advice",
    "created": "Sat May 30 05:16:47 +0000 2020",
    "tweets": 34962
  },
  {
    "username": "BitcoinFrogs",
    "name": "Bitcoin Frogs \u6bd4\u7279\u86d9",
    "bio": "10,000 timeless frog collectibles stored on Bitcoin blockchain. Chat: https://t.co/s6tG2QpYSQ. Market: https://t.co/CLkBgGbbcf",
    "followers": 64634,
    "following": 17786,
    "verified": true,
    "category": "ordinals",
    "url": "https://x.com/BitcoinFrogs",
    "location": "",
    "created": "Sun Feb 19 11:57:21 +0000 2023",
    "tweets": 18812
  },
  {
    "username": "FefeDemeny",
    "name": "Fefe Demeny",
    "bio": "\ud83d\udfe0 \u20bfitcoin since 2016 | \ud83d\udc10 of trading | Posts are opinions, nfa | Join The 100XClub Fam \ud83d\udd17 \ud83d\udc47",
    "followers": 63425,
    "following": 2148,
    "verified": true,
    "category": "ordinals",
    "url": "https://x.com/FefeDemeny",
    "location": "Planet Earth",
    "created": "Wed Apr 20 14:38:05 +0000 2016",
    "tweets": 20210
  },
  {
    "username": "Ben_Charbit",
    "name": "Ben Charbit",
    "bio": "Gaming and Bitcoin | CEO @Portalcoin | Ex @Ubisoft, BLIFE (merged), Darewise (exited), Lazard",
    "followers": 63365,
    "following": 1535,
    "verified": false,
    "category": "ordinals",
    "url": "https://x.com/Ben_Charbit",
    "location": "Paris, France",
    "created": "Mon Apr 08 21:45:24 +0000 2013",
    "tweets": 5638
  },
  {
    "username": "BitmonkCrypto",
    "name": "BitmonkCrypto",
    "bio": "#Bitcoin 2017 \ud83c\udf93 | #Crypto Investor, Advisor, Brand builder | Research-driven. Narrative-focused. Strategy-led | NFA | \ud83e\udeac Cut Down Emotions from Investing.",
    "followers": 62965,
    "following": 3997,
    "verified": true,
    "category": "ordinals",
    "url": "https://x.com/BitmonkCrypto",
    "location": "Telegram \u2014",
    "created": "Wed Nov 05 10:19:27 +0000 2014",
    "tweets": 12693
  },
  {
    "username": "WorldNfts",
    "name": "Worldian \ud83c\udf0e | AIIA",
    "bio": "Art aficionado | A.I. \u30a2\u30fc\u30c6\u30a3\u30b9\u30c8 | Art collector | Ordinals lover | Sci-Fi nerd | Exhibited in Rome, Paris, Beijing & New York | #AIIA",
    "followers": 57455,
    "following": 5943,
    "verified": true,
    "category": "ordinals",
    "url": "https://x.com/WorldNfts",
    "location": "A Galaxy far far away",
    "created": "Thu Mar 11 14:49:50 +0000 2021",
    "tweets": 69766
  },
  {
    "username": "jamkaa_mgl",
    "name": "Jamie* GodJira_gangz",
    "bio": "Human happiness and human satisfaction must ultimately come from within oneself. \nCo-founder @PGgroup_ @iAgentProtocol @JirasanOfficial",
    "followers": 54124,
    "following": 2286,
    "verified": true,
    "category": "ordinals",
    "url": "https://x.com/jamkaa_mgl",
    "location": "Godjira Island",
    "created": "Wed Sep 16 14:15:05 +0000 2009",
    "tweets": 1505
  },
  {
    "username": "omega_alpha_nft",
    "name": "Omega Alpha",
    "bio": "Private NFT & Web3 Alpha Community operated by @LegatoFP\nMembers get access to the best $ETH $BTC $SOL WLs & opportunities.\n\n@SeedifyFund Partner\n\n\u00a9\ufe0f2021",
    "followers": 54026,
    "following": 4216,
    "verified": true,
    "category": "ordinals",
    "url": "https://x.com/omega_alpha_nft",
    "location": "https://side.xyz/legato",
    "created": "Thu Nov 25 04:59:50 +0000 2021",
    "tweets": 2260
  },
  {
    "username": "BobBodily",
    "name": "Bob Bodily / Bitcoin DeFi \ud83e\uddd9\ud83c\udffd\u200d\u2642\ufe0f",
    "bio": "Bitcoin Expert \u2022 Degen \u2022 Educator \u2022 \n\nOnboarding 1M users to Bitcoin DeFi: \ud83d\udfe9\ud83d\udfe9\ud83d\udfe9\ud83d\udfe9\ud83d\udfe8\u2b1c\ufe0f\u2b1c\ufe0f\u2b1c\ufe0f\u2b1c\ufe0f\u2b1c\ufe0f (40.2%)",
    "followers": 52891,
    "following": 5073,
    "verified": true,
    "category": "ordinals",
    "url": "https://x.com/BobBodily",
    "location": "Do more w/ your Bitcoin \u27a1\ufe0f",
    "created": "Sun Apr 05 20:31:11 +0000 2015",
    "tweets": 12909
  },
  {
    "username": "charleskoh",
    "name": "Charles \ud83d\udc51",
    "bio": "head of growth | digital assets | stocks | \u20bf \u2604\ufe0f",
    "followers": 52305,
    "following": 14976,
    "verified": true,
    "category": "ordinals",
    "url": "https://x.com/charleskoh",
    "location": "The Garden",
    "created": "Wed Jan 21 08:14:22 +0000 2009",
    "tweets": 63214
  },
  {
    "username": "BR4ted",
    "name": "\u20bf\ud83e\uddde\u200d\u2642\ufe0f",
    "bio": "Director of Alpha at \u20bf-R4ted Community. Marketing nerd by habit, Advisor by choice.",
    "followers": 50853,
    "following": 3250,
    "verified": true,
    "category": "ordinals",
    "url": "https://x.com/BR4ted",
    "location": "Just a \u20bf-R4ted guy",
    "created": "Thu Dec 02 11:30:59 +0000 2021",
    "tweets": 65925
  },
  {
    "username": "Greekdx",
    "name": "Giannis Sourdis (\ud83e\udd89,\ud83e\udd89)",
    "bio": "\ud83e\udd89Investing @AmplifyGlobal \ud83c\udf0d Collecting @MuseumOfNFTARt @NarcissusGLRY \ud83c\udfa8 Building @couch_heroes \ud83d\udecb\ufe0f Vive \u03bba R\u00e9sistance #Bitcoin",
    "followers": 50278,
    "following": 4570,
    "verified": true,
    "category": "ordinals",
    "url": "https://x.com/Greekdx",
    "location": "Metaverse",
    "created": "Thu Dec 25 19:15:01 +0000 2014",
    "tweets": 51710
  },
  {
    "username": "utxord",
    "name": "UTXORD",
    "bio": "The only Genetic Launchpad for Ordinals. \nWe enable lazy minting, secured by Bitcoin Provenance. \nTrustless. Artistic. Social.",
    "followers": 50090,
    "following": 1191,
    "verified": false,
    "category": "ordinals",
    "url": "https://x.com/utxord",
    "location": "Borderless",
    "created": "Fri Jun 02 04:55:10 +0000 2023",
    "tweets": 887
  },
  {
    "username": "zacxbt",
    "name": "zac.eth \ud83e\uddd9\ud83c\udffb\u200d\u2642\ufe0f\u2666\ufe0f",
    "bio": "Bitcoin, DeSci, AI, Vibe, Design, Music, OhBabyGames | Founder @coinquariumgg (not financial advice)",
    "followers": 49482,
    "following": 13929,
    "verified": true,
    "category": "ordinals",
    "url": "https://x.com/zacxbt",
    "location": "",
    "created": "Mon Jul 17 01:53:17 +0000 2017",
    "tweets": 37527
  },
  {
    "username": "OVGNFT",
    "name": "Dr.OVG",
    "bio": "Angel Investor \n\nInner Circle\n\nFounder @DrAlphaweb3 | @ordinalcarrots | \n\nAmbassador | Advisor",
    "followers": 48429,
    "following": 15123,
    "verified": true,
    "category": "ordinals",
    "url": "https://x.com/OVGNFT",
    "location": null,
    "created": "Thu Feb 04 12:53:30 +0000 2016",
    "tweets": 138691
  },
  {
    "username": "eferrariph",
    "name": "Emanuele Ferrari",
    "bio": "@Superrare / @ndmstudio / emanueleferrari.eth / 0x830 \ud83d\udd34 / @admit0001 \ud83c\udf9f\ufe0f/ https://t.co/EiT8aW7TbL / Inscription #67156 / Bitcoin Punk #5770",
    "followers": 47263,
    "following": 3006,
    "verified": true,
    "category": "ordinals",
    "url": "https://x.com/eferrariph",
    "location": "Italy",
    "created": "Sat Jun 13 04:36:11 +0000 2009",
    "tweets": 19612
  },
  {
    "username": "tall_data",
    "name": "Tall",
    "bio": "Business News & Satirical Content. CMO @doginaldogs. True wisdom is in knowing you know nothing",
    "followers": 45567,
    "following": 9889,
    "verified": true,
    "category": "ordinals",
    "url": "https://x.com/tall_data",
    "location": "Doginal Dogs",
    "created": "Thu Dec 14 15:55:49 +0000 2023",
    "tweets": 26619
  },
  {
    "username": "cl_art_studio",
    "name": "CL Art Studio",
    "bio": "Designer of the #Runestone : 100% volunteer airdrop. Art Exhibited in multiple museums & art fairs. \nNow building \u2192  https://t.co/xU5qmE0DKA",
    "followers": 44990,
    "following": 4036,
    "verified": true,
    "category": "ordinals",
    "url": "https://x.com/cl_art_studio",
    "location": "Paris",
    "created": "Sun Feb 14 19:58:59 +0000 2010",
    "tweets": 2741
  },
  {
    "username": "0xSpop",
    "name": "0xSodapop",
    "bio": "Serial Entrepreneur | Over +15 Companies under management | \nEarly BTC Investor | AI & Blockchain enthusiast\n \n@Thesodaverse Founder",
    "followers": 43779,
    "following": 2967,
    "verified": true,
    "category": "ordinals",
    "url": "https://x.com/0xSpop",
    "location": "",
    "created": "Wed Jun 01 01:21:43 +0000 2022",
    "tweets": 7883
  },
  {
    "username": "CG_BRC20",
    "name": "CG \u25c9 #34566",
    "bio": "\u62d3\u5c55\u4f60\u7684\u601d\u7ef4\u8fb9\u754c\uff0c\u6311\u6218\u4f60\u7684\u8ba4\u77e5\u6781\u9650\u3002\u4fdd\u6301\u597d\u5947\uff0c\u4e0d\u65ad\u5b66\u4e60\uff0c\u8ba9\u81ea\u5df1\u6210\u4e3a\u4e0d\u65ad\u8fdb\u5316\u7684\u7248\u672c\u3002 \n\n#OKX\uff1ahttps://t.co/WicG27p0W7\n\n#Bitcoin #Ordinals",
    "followers": 42984,
    "following": 2597,
    "verified": true,
    "category": "ordinals",
    "url": "https://x.com/CG_BRC20",
    "location": "\u4fdd\u59c6\u6559\u7a0b\u94fe\u63a5\u603b\u6c47\u27a1\ufe0f",
    "created": "Tue Aug 03 06:37:25 +0000 2021",
    "tweets": 9622
  },
  {
    "username": "ALIENQUEENNFT",
    "name": "ALIENQUEEN",
    "bio": "Artist / Bitcoin & Freedom Maxi \ud83e\udd85\ud83c\uddfa\ud83c\uddf8\ud83c\uddf0\ud83c\udded\ud83c\udde8\ud83c\uddfa\u271d\ufe0f/ Punk 8149 / Collabs: Gucci / SnoopDogg / Red Bull Racing / Ubisoft / \u20bfTC $BTC $ETH $REKT",
    "followers": 42518,
    "following": 1888,
    "verified": true,
    "category": "ordinals",
    "url": "https://x.com/ALIENQUEENNFT",
    "location": "USA",
    "created": "Wed Mar 03 17:58:14 +0000 2021",
    "tweets": 80819
  },
  {
    "username": "ImGroot66",
    "name": "ImGroot \ud83e\uddf2",
    "bio": "Brand Manager\ud83e\udd96@PGgroup_  @JirasanOfficial\nCo-FOunder @ZaxWeb3\nTeam @Theordinalsclub",
    "followers": 42345,
    "following": 4188,
    "verified": true,
    "category": "ordinals",
    "url": "https://x.com/ImGroot66",
    "location": "JiraVerse",
    "created": "Thu Mar 04 14:46:33 +0000 2010",
    "tweets": 6452
  },
  {
    "username": "tugbachain",
    "name": "Tu\u011fba T\u00fcrker",
    "bio": "| Galatasaray_Uni M.A | Izmir Eko. Uni BA | @cryptoquant_com |@bitcoinmagpro | paylasmlr yat\u0131rm tavsiyesi de\u011fildr TG: https://t.co/Qv2jE0HhA4 IG: tugbaturkerrr",
    "followers": 41048,
    "following": 1382,
    "verified": true,
    "category": "ordinals",
    "url": "https://x.com/tugbachain",
    "location": "Arven",
    "created": "Tue Jul 19 20:39:29 +0000 2011",
    "tweets": 5637
  },
  {
    "username": "congge918",
    "name": "\u806a\u54e5.sats",
    "bio": "\u4e28@U9_BlockChain Co-founder\n\u4e28Ambassador for @injective @MorphNetwork @TheoriqAI \n\u4e28 #Binance \u8fd13\u4ebf\u9009\u62e9\uff1ahttps://t.co/iHW5AKstIE",
    "followers": 38845,
    "following": 4145,
    "verified": true,
    "category": "ordinals",
    "url": "https://x.com/congge918",
    "location": "\u5546\u52a1\u5408\u4f5c\u27a1",
    "created": "Wed Sep 07 21:12:55 +0000 2011",
    "tweets": 39671
  },
  {
    "username": "LeatherBTC",
    "name": "Leather - Grow your Bitcoin",
    "bio": "An open-source, self-custodial wallet for earning yield with Bitcoin, STX, sBTC & more. Transparent & intuitive across browser, mobile & desktop.",
    "followers": 38620,
    "following": 807,
    "verified": true,
    "category": "ordinals",
    "url": "https://x.com/LeatherBTC",
    "location": "Install for free \u2192",
    "created": "Fri Nov 11 11:38:18 +0000 2022",
    "tweets": 9926
  },
  {
    "username": "TheBitLeroy",
    "name": "Crypto Leroy",
    "bio": "#Bitcoin & #crypto since 2016 | Hodler | Ph.D in shitpost | #BTC #XRP #crypto Educator | GEM Hunter |#Defi + #NFT |  Not Financial Adviser... JOIN TG CHANNEL \ud83d\udc47",
    "followers": 37770,
    "following": 5814,
    "verified": true,
    "category": "ordinals",
    "url": "https://x.com/TheBitLeroy",
    "location": "MARS  \u27a1\ufe0f",
    "created": "Tue Sep 22 21:32:20 +0000 2009",
    "tweets": 72816
  },
  {
    "username": "janbtc",
    "name": "Jan",
    "bio": "Building @Xverse @Satsdaq | \ud83c\udf99\ufe0fHost @TheOrdinalShow | Founder @btc_summit | \ud83e\udd16 Student of AI",
    "followers": 37266,
    "following": 2797,
    "verified": true,
    "category": "ordinals",
    "url": "https://x.com/janbtc",
    "location": "",
    "created": "Wed Aug 08 19:44:44 +0000 2012",
    "tweets": 71195
  },
  {
    "username": "RAF_BTC",
    "name": "RAF",
    "bio": "Bitcoin since 2019, on-chain experimenter. Majors trader",
    "followers": 36903,
    "following": 4120,
    "verified": true,
    "category": "ordinals",
    "url": "https://x.com/RAF_BTC",
    "location": "",
    "created": "Sun Dec 27 13:35:08 +0000 2020",
    "tweets": 4659
  },
  {
    "username": "ssheyii",
    "name": "ssheyii",
    "bio": "\u21a0 Building: @Dineroxyz & @SsheyiiStation | Marketing Strategist | Ordinals/BTC Eco | Baddie - @PolyBaddies",
    "followers": 36545,
    "following": 2355,
    "verified": true,
    "category": "ordinals",
    "url": "https://x.com/ssheyii",
    "location": "Ssheyii Station\u26fd\ufe0f ",
    "created": "Sat Aug 27 10:06:31 +0000 2022",
    "tweets": 25806
  },
  {
    "username": "0xBaze",
    "name": "Ghosthand.sats \ud83d\udc09\ud83e\udd16\u30dc\u30c3",
    "bio": "\u21a0 Creator, Collab Manager, Space host\n\nGrinds for a living",
    "followers": 35267,
    "following": 4011,
    "verified": true,
    "category": "ordinals",
    "url": "https://x.com/0xBaze",
    "location": "Web3, Sleep in discord",
    "created": "Sat Nov 16 20:43:58 +0000 2019",
    "tweets": 147226
  },
  {
    "username": "ScrillaVentura",
    "name": "RARE SCRILLA",
    "bio": "Artist / Music Producer / Everything Fake / @fakerares_xcp / @beatblocksbtc / https://t.co/dWQV9DG8sv / new website coming soon",
    "followers": 35041,
    "following": 2739,
    "verified": true,
    "category": "ordinals",
    "url": "https://x.com/ScrillaVentura",
    "location": "Des Moines IOWA",
    "created": "Wed Dec 31 01:44:30 +0000 2008",
    "tweets": 72973
  },
  {
    "username": "SatoshisMom",
    "name": "Satoshi\u2019s Mom",
    "bio": "Artist and Founding Director of The Digital Asset Museum @theDAMmuseum",
    "followers": 34087,
    "following": 6686,
    "verified": true,
    "category": "ordinals",
    "url": "https://x.com/SatoshisMom",
    "location": "",
    "created": "Fri Mar 19 06:21:25 +0000 2021",
    "tweets": 32428
  },
  {
    "username": "0xPaomo",
    "name": "Bubble\ud83e\udee7\ud83e\ude75",
    "bio": "\ud83e\udee7\u795e\u79d8web3\u5973\u5927\uff5c\u533a\u5757\u94fe\u7231\u597d\u8005\uff5c\u53bb\u4e2d\u5fc3\u5316\u68a6\u60f3\u5bb6\uff5cNFT\u6536\u85cf\u8005\uff5c\u94bb\u77f3\u624b\uff5c\u6295\u7814\u5206\u6790\uff5c\u9879\u76ee\u63a8\u5e7f\uff5cBTC ETH SOL \u957f\u671f\u6301\u6709\uff5c\u7a7f\u8d8a\u725b\u718a\u5e02\uff5c\u6240\u6709\u6587\u7ae0\u5747\u4e0d\u662f\u6295\u8d44\u5efa\u8bae\uff5c\u79c1\u4fe1\u5408\u4f5c\uff1ahttps://t.co/bByCQUl6BP \ud83e\udee7",
    "followers": 33836,
    "following": 13736,
    "verified": true,
    "category": "ordinals",
    "url": "https://x.com/0xPaomo",
    "location": null,
    "created": "Mon Jan 16 18:47:41 +0000 2023",
    "tweets": 50721
  },
  {
    "username": "CharlieHusats",
    "name": "CharlieHu.sats",
    "bio": "AI Era, Judgment, Taste, Patience, Perspective.\nBitlayer YBTC | ex Polkadot | ex Polygon",
    "followers": 33299,
    "following": 3411,
    "verified": true,
    "category": "ordinals",
    "url": "https://x.com/CharlieHusats",
    "location": "Bitcoin History",
    "created": "Fri Apr 25 12:39:58 +0000 2014",
    "tweets": 2520
  },
  {
    "username": "bestinslotxyz",
    "name": "Best in Slot | BRC2.0 \ud83e\uddd1\u200d\ud83c\udf73",
    "bio": "\u25c9 Lead Maintainers of #BRC20\n\n\u25c9 Architects of BRC2.0 \u2014 bringing EVM smart-contracts and #DeFi to Bitcoin L1.\n\n\u25c9 Launch on @CoinCookercom | Trade on BiS DEX",
    "followers": 33201,
    "following": 397,
    "verified": false,
    "category": "ordinals",
    "url": "https://x.com/bestinslotxyz",
    "location": "Bitcoin",
    "created": "Sat Mar 16 08:41:38 +0000 2019",
    "tweets": 2905
  },
  {
    "username": "baladasathar",
    "name": "SATHAR",
    "bio": "\ud835\udd7e\ud835\udd86\ud835\udd99\ud835\udd8d\ud835\udd86\ud835\udd97 \ud835\udd8e\ud835\udd93 \ud835\udd92\ud835\udd8a \ud835\udd8e\ud835\udd98 \ud835\udd99\ud835\udd8d\ud835\udd8a \ud835\udd7e\ud835\udd86\ud835\udd99\ud835\udd8d\ud835\udd86\ud835\udd97 \ud835\udd8e\ud835\udd93 \ud835\udd9e\ud835\udd94\ud835\udd9a",
    "followers": 32881,
    "following": 2220,
    "verified": true,
    "category": "ordinals",
    "url": "https://x.com/baladasathar",
    "location": "",
    "created": "Sun Oct 10 14:41:50 +0000 2010",
    "tweets": 39170
  },
  {
    "username": "davidlin_",
    "name": "David Lin \ud83d\udfe7",
    "bio": "Co-founder of @Ordzaar \ud83d\udfe7 Organizer of @OrdinalsSummit \ud83d\udfe7 Ordinals \u25a3 Building on #Bitcoin \u25a3 Supporting Artists \ud83c\udfa8\ud83e\udde1 \u25a3",
    "followers": 32737,
    "following": 1182,
    "verified": true,
    "category": "ordinals",
    "url": "https://x.com/davidlin_",
    "location": "",
    "created": "Sun Nov 22 21:49:52 +0000 2015",
    "tweets": 717
  },
  {
    "username": "TroyCaylak",
    "name": "TROY \u260e\ufe0f",
    "bio": "Writer\ud83d\udd38Actor\ud83d\udd38Founder @Ordinauts @Ordzaar @Retordinals\ud83d\udd38Story Advisor\ud83d\udd38@Pizzaninjas \ud83d\udd38Content Creator\ud83d\udd38Meme Explorer\ud83d\udd38King of Suckballs Mountain\ud83d\udd38",
    "followers": 32706,
    "following": 4053,
    "verified": true,
    "category": "ordinals",
    "url": "https://x.com/TroyCaylak",
    "location": "Los Angeles",
    "created": "Sun May 09 15:31:17 +0000 2010",
    "tweets": 56809
  },
  {
    "username": "erikalee",
    "name": "Erika Lee",
    "bio": "writing abt markets, culture, & books | contrib. @decryptmedia @okx etc | prev: @btcfrontierfund @vaynermedia @cbsnews @usc | book: https://t.co/ZuWPy3nakA",
    "followers": 31570,
    "following": 18598,
    "verified": true,
    "category": "ordinals",
    "url": "https://x.com/erikalee",
    "location": "highlights tab ",
    "created": "Sun Apr 05 16:35:03 +0000 2009",
    "tweets": 29609
  },
  {
    "username": "artbyvoka",
    "name": "VOKA",
    "bio": "Traditional artist using #BTC as a canvas. \n\nCreater of the Canvas to Code collection available on @MEonBTC\n\nhttps://t.co/oqFafp3K1G",
    "followers": 31558,
    "following": 212,
    "verified": false,
    "category": "ordinals",
    "url": "https://x.com/artbyvoka",
    "location": "Puchberg, Austria ",
    "created": "Thu Oct 06 20:55:44 +0000 2022",
    "tweets": 518
  },
  {
    "username": "billydollarcat",
    "name": "Billy \ud83d\udc31",
    "bio": "$BILLY to a billy on Bitcoin \u20bf) \ud83d\udd38 https://t.co/dEpK5RhzGi",
    "followers": 31422,
    "following": 2689,
    "verified": true,
    "category": "ordinals",
    "url": "https://x.com/billydollarcat",
    "location": "Bitcoin",
    "created": "Fri May 17 05:40:14 +0000 2024",
    "tweets": 13992
  },
  {
    "username": "Brrrraad",
    "name": "\u20bfrad \ud83d\udc51",
    "bio": "",
    "followers": 31206,
    "following": 5659,
    "verified": true,
    "category": "ordinals",
    "url": "https://x.com/Brrrraad",
    "location": "",
    "created": "Sat Aug 28 02:43:38 +0000 2021",
    "tweets": 6884
  },
  {
    "username": "rationalaussie",
    "name": "Rational Aussie",
    "bio": "Humans are fungible compute. I write about economics and AI. Fix the money, fix the world.\n\n#Bitcoin",
    "followers": 31170,
    "following": 6986,
    "verified": true,
    "category": "ordinals",
    "url": "https://x.com/rationalaussie",
    "location": null,
    "created": "Thu Sep 01 09:05:18 +0000 2011",
    "tweets": 41540
  },
  {
    "username": "casperdefi",
    "name": "Casper \ud83e\udd87\ud83d\udd0a",
    "bio": "\ud83e\uddea@fruitsquarex Partner @ https://t.co/Hq3VtsrwzU\n I dont work #BTC does. Tweets are not financial advice. ALWAYS #DYOR Discord: casperdefi#8379",
    "followers": 30006,
    "following": 12540,
    "verified": true,
    "category": "ordinals",
    "url": "https://x.com/casperdefi",
    "location": "Ghostland",
    "created": "Thu Jul 23 19:02:22 +0000 2009",
    "tweets": 26790
  },
  {
    "username": "CryptoPopPunk",
    "name": "Pop Punk",
    "bio": "Howdy! @NewWaveSurfClub -- Artist County Fair\ud83c\udfa1Las Vegas\ud83c\udfb0Rubber\ud83c\udfc1Climbing\ud83e\udde0, collector & NFT security instructor -- Cryptopunk 6978 +2 -- BTC 2012, ETH 2015",
    "followers": 29616,
    "following": 1449,
    "verified": true,
    "category": "ordinals",
    "url": "https://x.com/CryptoPopPunk",
    "location": "",
    "created": "Wed Sep 28 10:36:22 +0000 2011",
    "tweets": 142580
  },
  {
    "username": "billyrestey",
    "name": "billy restey",
    "bio": "digital artist \u25c9 sold at @sothebys | featured in @wired | pioneering a path on \u20bfitcoin",
    "followers": 29435,
    "following": 3742,
    "verified": true,
    "category": "ordinals",
    "url": "https://x.com/billyrestey",
    "location": "Bitcoin",
    "created": "Wed Jul 13 23:36:26 +0000 2011",
    "tweets": 29635
  },
  {
    "username": "EmpressTrash",
    "name": "Empress Trash \ud83c\udf08\ud83d\udda4",
    "bio": "multiversatile artist | chaotic neutral | debris of the avant-garde | #glitch #ai #painting #crypto #art #cc0 https://t.co/lBvL9H5kZf",
    "followers": 29312,
    "following": 6370,
    "verified": true,
    "category": "ordinals",
    "url": "https://x.com/EmpressTrash",
    "location": "Mexico City",
    "created": "Tue Apr 28 01:33:23 +0000 2020",
    "tweets": 147912
  },
  {
    "username": "Ordinal_News",
    "name": "Ordinal News \ud83d\udfe0",
    "bio": "Everything about Bitcoin Ordinals & Runes\nNews, Tutorials, Events, Guides, Tools, Upcoming\ud83d\udca7",
    "followers": 29164,
    "following": 1048,
    "verified": true,
    "category": "ordinals",
    "url": "https://x.com/Ordinal_News",
    "location": "gm@OrdinalNews.io",
    "created": "Tue Mar 14 00:37:30 +0000 2023",
    "tweets": 25320
  },
  {
    "username": "theonlyposted",
    "name": "James (Posted) \ud83d\udef8",
    "bio": "Chief Idiot (Head of BD & HR) @LiquidiumWTF & @liquidiumFi\n\nCo-fndr of Beemer Fam (YT&IG)\n\n@BitcoinStarship\n\nPrev: @btcstartuplab @cointelegraph\n\n@umich Alum",
    "followers": 28617,
    "following": 5886,
    "verified": true,
    "category": "ordinals",
    "url": "https://x.com/theonlyposted",
    "location": "Pleiades ",
    "created": "Thu May 14 21:51:21 +0000 2009",
    "tweets": 88048
  },
  {
    "username": "GiulioAprin",
    "name": "Giulio Aprin",
    "bio": "Photographer, Explorer and Storyteller of Deserts. \nTransientLabs Curated | SuperRare | \u039e \u20bf since \u201821\nPortfolio https://t.co/LrlViuxR3G : : Stories https://t.co/8a6x5VHp6h",
    "followers": 28289,
    "following": 1992,
    "verified": true,
    "category": "ordinals",
    "url": "https://x.com/GiulioAprin",
    "location": "Desert",
    "created": "Wed Jun 24 20:21:09 +0000 2009",
    "tweets": 113230
  },
  {
    "username": "lodelascripto",
    "name": "lodelascripto (N\u00e9stor)",
    "bio": "Ambassador for @spectra_finance\n#BTC",
    "followers": 27723,
    "following": 6705,
    "verified": true,
    "category": "ordinals",
    "url": "https://x.com/lodelascripto",
    "location": "",
    "created": "Thu May 24 14:21:58 +0000 2018",
    "tweets": 74840
  },
  {
    "username": "SluttyNft",
    "name": "Sluttoshi",
    "bio": "Official Rat - @__O_M_L__\nCoFounder - @taprootalpha   \nTeam - @CONN3CTIVITY_  \nGetting Slutty on BTC",
    "followers": 27717,
    "following": 4035,
    "verified": true,
    "category": "ordinals",
    "url": "https://x.com/SluttyNft",
    "location": "",
    "created": "Sat Aug 27 01:46:40 +0000 2022",
    "tweets": 7985
  },
  {
    "username": "const_quary",
    "name": "quary.sats",
    "bio": "Founder of @Magisat_io (rare sats trustless marketplace) Blockchain degen and dev. creator of Quary's Masterworks: https://t.co/pJUzx1gpUp",
    "followers": 27080,
    "following": 1449,
    "verified": true,
    "category": "ordinals",
    "url": "https://x.com/const_quary",
    "location": "Romania",
    "created": "Tue May 03 17:24:34 +0000 2016",
    "tweets": 9435
  },
  {
    "username": "zetman_eth",
    "name": "zetman.bnb",
    "bio": "Angel Investor\nLead Engineer in semiconductor\nCo-founder @inkedbtc \nHodling Bitcoin\n2 Fur babies + 1 Baby girl",
    "followers": 26941,
    "following": 5730,
    "verified": true,
    "category": "ordinals",
    "url": "https://x.com/zetman_eth",
    "location": "San Francisco, CA",
    "created": "Wed Jul 27 03:18:10 +0000 2022",
    "tweets": 13447
  },
  {
    "username": "nullish",
    "name": "Nullish",
    "bio": "Building on Bitcoin.",
    "followers": 26826,
    "following": 1019,
    "verified": true,
    "category": "ordinals",
    "url": "https://x.com/nullish",
    "location": "Bitcoin",
    "created": "Tue Dec 26 13:59:44 +0000 2017",
    "tweets": 1132
  },
  {
    "username": "btcbongo",
    "name": "Bongo \ud83e\udd41",
    "bio": "Chief Degen Officer at @hashlingsBTC ||  @billydollarcat || @LaFamilia_so",
    "followers": 26327,
    "following": 7436,
    "verified": true,
    "category": "ordinals",
    "url": "https://x.com/btcbongo",
    "location": "",
    "created": "Tue Oct 11 18:07:08 +0000 2022",
    "tweets": 102369
  },
  {
    "username": "Satflow",
    "name": "Satflow",
    "bio": "Bitcoin for Pro Traders - Trade Bitcoin Tokens and NFTs at the speed of light, backed by @variantfund",
    "followers": 25534,
    "following": 172,
    "verified": false,
    "category": "ordinals",
    "url": "https://x.com/Satflow",
    "location": "Bitcoin",
    "created": "Tue Sep 26 21:09:14 +0000 2023",
    "tweets": 220
  },
  {
    "username": "TommyTwoClubs",
    "name": "Tom",
    "bio": "#1 collector of like-minded friends @RoomFourtyFour | @GoodDayBitcoin Money Markets & News M-F @ 9am EST",
    "followers": 25283,
    "following": 4955,
    "verified": true,
    "category": "ordinals",
    "url": "https://x.com/TommyTwoClubs",
    "location": "The Blockchain",
    "created": "Mon May 18 01:53:38 +0000 2020",
    "tweets": 111236
  },
  {
    "username": "Aizcalibur",
    "name": "Aiz",
    "bio": "Growth @playGigaverse @GLHFers \n\nPassionate about Bitcoin, gaming & systems thinking.\n\nI analyze complex systems & translate them into insightful infographics.",
    "followers": 24335,
    "following": 2583,
    "verified": true,
    "category": "ordinals",
    "url": "https://x.com/Aizcalibur",
    "location": null,
    "created": "Mon Jun 22 15:39:15 +0000 2020",
    "tweets": 50799
  },
  {
    "username": "floraforms",
    "name": "Flora Forms",
    "bio": "Merging cultural heritage with generative art on #Bitcoin\n\nA collaboration between @harto_fr and @belvederemuseum accelerated by @Artiesltd & @vivid_ordinals",
    "followers": 24075,
    "following": 396,
    "verified": false,
    "category": "ordinals",
    "url": "https://x.com/floraforms",
    "location": "Bitcoin",
    "created": "Thu Jan 18 15:34:40 +0000 2024",
    "tweets": 539
  },
  {
    "username": "DoggfatherCrew",
    "name": "Doggfather",
    "bio": "Bitcoin eco & DeFi analytics | Hosting Crunching Sats",
    "followers": 23990,
    "following": 6323,
    "verified": true,
    "category": "ordinals",
    "url": "https://x.com/DoggfatherCrew",
    "location": "",
    "created": "Sun Oct 10 10:39:06 +0000 2021",
    "tweets": 61539
  },
  {
    "username": "Halfourlabi",
    "name": "Ugly boy\ud83d\udd25\ud83d\udc3a\ud83e\uddbe",
    "bio": "Metabolite\ud83e\uddec \u00b6 degenerate \u00b6 bye banks, buy $BTC \u00b6 Building; @TrenchesDao, @Bofab_Dao @Elixir_hq",
    "followers": 23031,
    "following": 9764,
    "verified": true,
    "category": "ordinals",
    "url": "https://x.com/Halfourlabi",
    "location": "Blockchain",
    "created": "Wed Dec 13 00:45:58 +0000 2017",
    "tweets": 204052
  },
  {
    "username": "ihate1999",
    "name": "Abubakar Nur Khalil",
    "bio": "\ud83c\uddf3\ud83c\uddec \u20bfitcoin Core contributor | @rcrsvcapital | @btrustteam | @btrust_builders",
    "followers": 22692,
    "following": 1118,
    "verified": true,
    "category": "ordinals",
    "url": "https://x.com/ihate1999",
    "location": "{Redacted}",
    "created": "Sat Oct 30 19:13:12 +0000 2010",
    "tweets": 5317
  },
  {
    "username": "drjingle",
    "name": "Dr.Jingle\ud83e\udd9e\ud83e\udd80",
    "bio": "\u265b Founder of MS & M\u20bf  \n\u265b Build Small Stuff on Canton Network  \n\u265b Visiting Lecturer\n\u265b Chartered Builder",
    "followers": 22603,
    "following": 4728,
    "verified": true,
    "category": "ordinals",
    "url": "https://x.com/drjingle",
    "location": "M\u20bf",
    "created": "Tue Sep 05 12:05:42 +0000 2023",
    "tweets": 14926
  },
  {
    "username": "AsteroidLabsX",
    "name": "Asteroid",
    "bio": "ambassador @MaestroBots @CoinTerminalCom. Holder $ETH $BTC $WLFI $BNB",
    "followers": 21490,
    "following": 1685,
    "verified": true,
    "category": "ordinals",
    "url": "https://x.com/AsteroidLabsX",
    "location": "JAPAN",
    "created": "Sat Oct 02 05:13:13 +0000 2021",
    "tweets": 51283
  },
  {
    "username": "zijing",
    "name": "\u5b50\u656c",
    "bio": "\uff5cContent creator\u270d\ufe0f\n\uff5cMember @Solana_zh\ud83d\udfe3\n\uff5cHEAD CM @Element_Market\n\uff5cCM @unisat_wallet\n\uff5cAmbassadors @JupiterExchange @TraditioNow",
    "followers": 21285,
    "following": 3813,
    "verified": true,
    "category": "ordinals",
    "url": "https://x.com/zijing",
    "location": "collab\ud83d\udc49",
    "created": "Sun Jan 16 01:00:23 +0000 2022",
    "tweets": 41631
  },
  {
    "username": "ErnestCisneros1",
    "name": "Ernesto Cisneros",
    "bio": "#NFTartist #Spaceshost #Art  #Technology\n #NFTcommunity \n$ETH / $XTZ / $SOL / #BTC \n\u3010 \ud83c\udfb9+\ud83d\udda5\ufe0f+\u2665\ufe0f \u3011",
    "followers": 20968,
    "following": 17766,
    "verified": true,
    "category": "ordinals",
    "url": "https://x.com/ErnestCisneros1",
    "location": "Miami, FL",
    "created": "Wed Jun 24 12:39:34 +0000 2020",
    "tweets": 83775
  },
  {
    "username": "mewtwosats",
    "name": "Mewtwo.sats",
    "bio": "The circumstances of ones birth is irrelevent,it is what you do with the gift of life that determines who you are\n@OrdinalPokemon @RuneGuardians Collector\ud83d\udc8e",
    "followers": 20597,
    "following": 3653,
    "verified": false,
    "category": "ordinals",
    "url": "https://x.com/mewtwosats",
    "location": "Pallet Town",
    "created": "Fri Oct 15 20:23:13 +0000 2021",
    "tweets": 8674
  },
  {
    "username": "artbrock34",
    "name": "art\u20bfrock |\u26a1\ufe0f\ud83d\udd38",
    "bio": "Self-taught multi (chain x disciplinary) artist \ud83d\udc7e PhD \u2022 NFT'21 | \u2022 \ud835\udc02\ud835\udc32\ud835\udc1b\ud835\udc0e\ud835\udc2b\ud835\udc1d\ud835\udc2c\ud83e\udd16\n\n@GORDLabsNFT coming to @SuperRare \ud83d\udc8e 28th Jan  \n\nhttps://t.co/WmoiCU6C1k",
    "followers": 20483,
    "following": 9421,
    "verified": true,
    "category": "ordinals",
    "url": "https://x.com/artbrock34",
    "location": "Vorgia",
    "created": "Thu Sep 02 19:43:33 +0000 2021",
    "tweets": 62241
  },
  {
    "username": "PERFECTL00P",
    "name": "\u2591 perfectloop \u2591",
    "bio": "High Contrast // High Saturation //Gif Alchemist \ud83e\uddd9\u200d\u2642\ufe0f// Futurist // Maker of \ud83e\udd0c Loops //",
    "followers": 20358,
    "following": 1983,
    "verified": true,
    "category": "ordinals",
    "url": "https://x.com/PERFECTL00P",
    "location": "xyz",
    "created": "Fri Oct 15 18:18:20 +0000 2021",
    "tweets": 7405
  },
  {
    "username": "0xpipi",
    "name": "Pipi",
    "bio": "#\u8001\u4e2d\u4eba #minimalism \u552f\u5fc3 \u601d\u60f3\u5bb6 \u54f2\u5b66\u5bb6 \u62bd\u8c61 \u53d1\u766b \u9633\u75ff #BTC $DOGE $uni \u2022 \u1d17 \u2022 \ud83c\udf0d\u262e\ufe0f $pepe $mog \ud83e\udef5\ud83d\ude39",
    "followers": 20077,
    "following": 7168,
    "verified": true,
    "category": "ordinals",
    "url": "https://x.com/0xpipi",
    "location": "btc",
    "created": "Fri Dec 18 17:39:40 +0000 2020",
    "tweets": 5669
  },
  {
    "username": "Decentralizd",
    "name": "Degentralizd(\ud83c\udf0e\u262e\ufe0f\ud83c\udff4\u200d\u2620\ufe0f)",
    "bio": "All roads lead to Bitcoin Collectibles.\n\nStuff I do: @OrdXCom @PuppetCorpbtw @OrdinuhlWassies @DevaultCrypto\n\n@BitcoinPuppets Janny\nSovereignty Maxi\n\ud83c\udf0e\u262e\ufe0f\ud83c\udff4\u200d\u2620\ufe0f",
    "followers": 20076,
    "following": 5274,
    "verified": true,
    "category": "ordinals",
    "url": "https://x.com/Decentralizd",
    "location": "Earth, Milky Way Galaxy",
    "created": "Wed Dec 16 02:13:26 +0000 2015",
    "tweets": 88376
  },
  {
    "username": "ReeceSwanepoel",
    "name": "ReeceSwanepoel.btc \ud83d\udfe7",
    "bio": "Maker of lines |||| Building @theblockweb |||| \ud83d\ude3c \u271d\ufe0f",
    "followers": 20063,
    "following": 14649,
    "verified": true,
    "category": "ordinals",
    "url": "https://x.com/ReeceSwanepoel",
    "location": "Africa",
    "created": "Wed Aug 05 17:41:48 +0000 2020",
    "tweets": 189817
  },
  {
    "username": "cryptoseanx",
    "name": "Cryptosean",
    "bio": "buy btc since 2010\uff0cNFT since 2017.crypto believer,and Diamond holder.",
    "followers": 19868,
    "following": 3146,
    "verified": true,
    "category": "ordinals",
    "url": "https://x.com/cryptoseanx",
    "location": "\u9999\u6e2f",
    "created": "Tue Oct 06 14:36:16 +0000 2015",
    "tweets": 3001
  },
  {
    "username": "MemphisBTC",
    "name": "Memphis \ud83e\udec0",
    "bio": "Immortal by inscription\nDeath cannot kill that which is eternal\n\nSHINIGAMI:\nhttps://t.co/aoQq7Rcr6t",
    "followers": 19530,
    "following": 733,
    "verified": true,
    "category": "ordinals",
    "url": "https://x.com/MemphisBTC",
    "location": "Artist",
    "created": "Mon Nov 22 05:43:21 +0000 2021",
    "tweets": 10139
  },
  {
    "username": "josephineweb3",
    "name": "Josephine (sol/acc)",
    "bio": "PhD in Internet Money Printing / Memecoin Maxi $MOG $FWOG #RETARDIO $APU $GIGA $POPCAT #BITCOIN #SPX6900",
    "followers": 19037,
    "following": 11145,
    "verified": true,
    "category": "ordinals",
    "url": "https://x.com/josephineweb3",
    "location": "",
    "created": "Sat Oct 26 06:06:56 +0000 2013",
    "tweets": 58753
  },
  {
    "username": "NolchaShows",
    "name": "NOLCHA",
    "bio": "Culture-driven experiences during leading Crypto Conferences \u2728 \u27a1\ufe0f Next CONSENSUS HONG KONG & BTC VEGAS  \ud83d\udca5 As featured in @coindesk @wwd @vogue",
    "followers": 18730,
    "following": 12700,
    "verified": false,
    "category": "ordinals",
    "url": "https://x.com/NolchaShows",
    "location": "New York City",
    "created": "Wed Dec 03 16:25:55 +0000 2008",
    "tweets": 26628
  },
  {
    "username": "realizingerin",
    "name": "erin",
    "bio": "Bitcoin Astrologer @hellmoneypod @inscribatlantis\n2026 readings now open \ud83e\udef3",
    "followers": 18596,
    "following": 1196,
    "verified": true,
    "category": "ordinals",
    "url": "https://x.com/realizingerin",
    "location": null,
    "created": "Wed Oct 19 03:34:33 +0000 2022",
    "tweets": 6419
  }
]